ipc/__init__.py
ipc/worker.py
simple_ipc-1.2.1.dist-info/LICENSE
simple_ipc-1.2.1.dist-info/METADATA
simple_ipc-1.2.1.dist-info/WHEEL
simple_ipc-1.2.1.dist-info/top_level.txt
simple_ipc-1.2.1.dist-info/RECORD
