Metadata-Version: 2.1
Name: simple-ipc
Version: 1.2.1
Summary: Inter-process communication based on stdio
Home-page: https://github.com/celltec/simple-ipc
Author: Jeremy Peters
Author-email: contact@celltec.dev
License: UNKNOWN
Project-URL: Source, https://github.com/celltec/simple-ipc/tree/master/src/ipc/worker.py
Keywords: ipc stdio stdin stdout send process program communicate interact transmit transfer communication interaction transmission simple
Platform: UNKNOWN
Classifier: License :: OSI Approved :: MIT License
Classifier: Programming Language :: Python :: 2.7
Classifier: Programming Language :: Python :: 3
Requires-Python: >=2.7, <4
